syrkis/__init__.py
syrkis/data/__init__.py
syrkis/data/datasets.py
syrkis/plot/__init__.py
syrkis/plot/images.html
syrkis/plot/plot.py
syrkis/train/__init__.py
syrkis/train/utils.py
syrkis-0.1.0.dist-info/METADATA
syrkis-0.1.0.dist-info/WHEEL
syrkis-0.1.0.dist-info/RECORD
