Metadata-Version: 2.1
Name: syrkis
Version: 0.1.0
Summary: 
Author: Noah Syrkis
Author-email: noah@syrkis.com
Requires-Python: >=3.11,<3.12
Classifier: Programming Language :: Python :: 3
Classifier: Programming Language :: Python :: 3.11
Requires-Dist: jax (>=0.4.31,<0.5.0)
Requires-Dist: jupyterlab (>=4.2.5,<5.0.0)
Requires-Dist: pillow (>=10.4.0,<11.0.0)
